{
  "openapi": "3.0.3",
  "info": {
    "title": "Student Skill Exchange API",
    "description": "Backend API for the Skill Exchange platform. Auth (register/login), Users CRUD with RBAC, transactions (match-request, paid-exchange, confirm-form2), **matching** (Form 1 / Form 2 eligibility), universities, skills, exchanges, sessions, reviews, portfolio, payments. Protected routes require Authorization: Bearer <JWT>.\n\n## Live Chat (real-time)\n- **Send message:** REST only — POST /api/v1/conversations/{id}/messages with body { \"content\": \"...\" }. After saving, the server emits the same message over Socket.io to the conversation room so the other participant sees it in real time.\n- **Exchange readiness:** PATCH /api/v1/conversations/{id}/exchange-readiness with { \"ready\": true|false }; server emits `exchange_readiness` to the conversation room (same join as chat).\n- **Socket.io:** Same origin as API (e.g. http://localhost:5000). Auth: handshake with auth.token = 'Bearer <JWT>' or query token=<JWT>. Events: emit 'join_conversation' with { conversationId } to join (student, participant only); emit 'leave_conversation' with { conversationId }; listen 'message' for new messages; listen 'exchange_readiness' for Form 2 slider sync. See backend/docs/LIVE-CHAT.md for testing.",
    "version": "1.0.0"
  },
  "servers": [
    {
      "url": "http://localhost:5000",
      "description": "Local dev"
    }
  ],
  "paths": {
    "/api/v1/health": {
      "get": {
        "summary": "Health check",
        "tags": ["Health"],
        "responses": {
          "200": {
            "description": "API is healthy",
            "content": {
              "application/json": {
                "schema": { "$ref": "#/components/schemas/HealthResponse" }
              }
            }
          }
        }
      }
    },
    "/api/v1/auth/register": {
      "post": {
        "summary": "Register",
        "description": "Create a new account. If universityId is provided, creates a Student row so the user gets role student.",
        "tags": ["Auth"],
        "requestBody": {
          "required": true,
          "content": {
            "application/json": {
              "schema": { "$ref": "#/components/schemas/RegisterRequest" }
            }
          }
        },
        "responses": {
          "201": {
            "description": "Registered",
            "content": {
              "application/json": {
                "schema": { "$ref": "#/components/schemas/AuthResponse" }
              }
            }
          },
          "400": {
            "description": "Validation error or email already in use",
            "content": {
              "application/json": {
                "schema": { "$ref": "#/components/schemas/ErrorResponse" }
              }
            }
          }
        }
      }
    },
    "/api/v1/auth/login": {
      "post": {
        "summary": "Login",
        "description": "Validate email/password and return user and JWT.",
        "tags": ["Auth"],
        "requestBody": {
          "required": true,
          "content": {
            "application/json": {
              "schema": { "$ref": "#/components/schemas/LoginRequest" }
            }
          }
        },
        "responses": {
          "200": {
            "description": "Logged in",
            "content": {
              "application/json": {
                "schema": { "$ref": "#/components/schemas/AuthResponse" }
              }
            }
          },
          "401": {
            "description": "Invalid email or password",
            "content": {
              "application/json": {
                "schema": { "$ref": "#/components/schemas/ErrorResponse" }
              }
            }
          }
        }
      }
    },
    "/api/v1/users/me": {
      "get": {
        "summary": "Current user",
        "description": "Returns the authenticated user (from JWT).",
        "tags": ["Users"],
        "security": [{ "bearerAuth": [] }],
        "responses": {
          "200": {
            "description": "Current user",
            "content": {
              "application/json": {
                "schema": { "$ref": "#/components/schemas/SingleUserResponse" }
              }
            }
          },
          "401": {
            "description": "Unauthorized",
            "content": {
              "application/json": {
                "schema": { "$ref": "#/components/schemas/ErrorResponse" }
              }
            }
          }
        }
      }
    },
    "/api/v1/users": {
      "get": {
        "summary": "List users",
        "description": "Superadmin: all users; Admin: only their university students.",
        "tags": ["Users"],
        "security": [{ "bearerAuth": [] }],
        "responses": {
          "200": { "description": "List of users" },
          "401": {
            "description": "Unauthorized",
            "content": {
              "application/json": {
                "schema": { "$ref": "#/components/schemas/ErrorResponse" }
              }
            }
          },
          "403": {
            "description": "Admin or Superadmin required",
            "content": {
              "application/json": {
                "schema": { "$ref": "#/components/schemas/ErrorResponse" }
              }
            }
          }
        }
      },
      "post": {
        "summary": "Create user",
        "description": "Admin or Superadmin (real signup is POST /auth/register).",
        "tags": ["Users"],
        "security": [{ "bearerAuth": [] }],
        "requestBody": {
          "required": true,
          "content": {
            "application/json": {
              "schema": {
                "type": "object",
                "required": ["name", "email"],
                "properties": {
                  "name": { "type": "string" },
                  "email": { "type": "string", "format": "email" }
                }
              }
            }
          }
        },
        "responses": {
          "201": { "description": "Created" },
          "400": {
            "description": "Validation error",
            "content": {
              "application/json": {
                "schema": { "$ref": "#/components/schemas/ErrorResponse" }
              }
            }
          },
          "401": { "description": "Unauthorized" },
          "403": { "description": "Forbidden" }
        }
      }
    },
    "/api/v1/users/{id}": {
      "get": {
        "summary": "Get user by ID",
        "description": "Self, or Superadmin, or Admin (students at their uni only).",
        "tags": ["Users"],
        "security": [{ "bearerAuth": [] }],
        "parameters": [
          { "name": "id", "in": "path", "required": true, "schema": { "type": "integer" } }
        ],
        "responses": {
          "200": { "description": "User" },
          "401": { "description": "Unauthorized" },
          "403": { "description": "Forbidden" },
          "404": { "description": "Not found" }
        }
      },
      "put": {
        "summary": "Update user",
        "description": "Self, or Superadmin, or Admin (students at their uni only).",
        "tags": ["Users"],
        "security": [{ "bearerAuth": [] }],
        "parameters": [
          { "name": "id", "in": "path", "required": true, "schema": { "type": "integer" } }
        ],
        "requestBody": {
          "required": true,
          "content": {
            "application/json": {
              "schema": {
                "type": "object",
                "required": ["name", "email"],
                "properties": {
                  "name": { "type": "string" },
                  "email": { "type": "string", "format": "email" }
                }
              }
            }
          }
        },
        "responses": {
          "200": { "description": "Updated" },
          "400": { "description": "Validation error" },
          "401": { "description": "Unauthorized" },
          "403": { "description": "Forbidden" },
          "404": { "description": "Not found" }
        }
      },
      "delete": {
        "summary": "Delete user",
        "description": "Superadmin only (platform-level action; university admin cannot delete accounts).",
        "tags": ["Users"],
        "security": [{ "bearerAuth": [] }],
        "parameters": [
          { "name": "id", "in": "path", "required": true, "schema": { "type": "integer" } }
        ],
        "responses": {
          "200": { "description": "Deleted" },
          "401": { "description": "Unauthorized" },
          "403": { "description": "Forbidden" },
          "404": { "description": "Not found" }
        }
      }
    },
    "/api/v1/transactions/match-request": {
      "post": {
        "summary": "Match request",
        "description": "Student only. Create exchange from offer + request + conversation.",
        "tags": ["Transactions"],
        "security": [{ "bearerAuth": [] }],
        "requestBody": {
          "required": true,
          "content": {
            "application/json": {
              "schema": {
                "type": "object",
                "required": ["offerId", "requestId", "conversationId", "scheduledStart", "scheduledEnd"],
                "properties": {
                  "offerId": { "type": "integer" },
                  "requestId": { "type": "integer" },
                  "conversationId": { "type": "integer" },
                  "scheduledStart": { "type": "string" },
                  "scheduledEnd": { "type": "string" }
                }
              }
            }
          }
        },
        "responses": {
          "201": {
            "description": "Created",
            "content": {
              "application/json": {
                "schema": { "$ref": "#/components/schemas/MatchRequestResponse" }
              }
            }
          },
          "400": { "description": "Validation error" },
          "401": { "description": "Unauthorized" },
          "403": { "description": "Student role required" }
        }
      }
    },
    "/api/v1/transactions/paid-exchange": {
      "post": {
        "summary": "Paid exchange",
        "description": "Student only. Record paid exchange.",
        "tags": ["Transactions"],
        "security": [{ "bearerAuth": [] }],
        "requestBody": {
          "required": true,
          "content": {
            "application/json": {
              "schema": {
                "type": "object",
                "required": ["exchangeId", "price"],
                "properties": {
                  "exchangeId": { "type": "integer" },
                  "price": { "type": "number", "minimum": 0.01 }
                }
              }
            }
          }
        },
        "responses": {
          "201": {
            "description": "Created",
            "content": {
              "application/json": {
                "schema": { "$ref": "#/components/schemas/PaidExchangeResponse" }
              }
            }
          },
          "400": { "description": "Validation error" },
          "401": { "description": "Unauthorized" },
          "403": { "description": "Student role required" }
        }
      }
    },
    "/api/v1/transactions/confirm-form2": {
      "post": {
        "summary": "Confirm exchange (Form 2)",
        "description": "Student only, participant only. Requires both students to have PATCHed exchange-readiness ready. Creates one or more Exchange + Session rows; VideoSession if online; PaidExchange + Payment if paid. Resets readiness flags after success.",
        "tags": ["Transactions"],
        "security": [{ "bearerAuth": [] }],
        "requestBody": {
          "required": true,
          "content": {
            "application/json": {
              "schema": { "$ref": "#/components/schemas/ConfirmForm2Request" }
            }
          }
        },
        "responses": {
          "201": {
            "description": "Created",
            "content": {
              "application/json": {
                "schema": { "$ref": "#/components/schemas/ConfirmForm2Response" }
              }
            }
          },
          "400": { "description": "Validation or business rule error" },
          "401": { "description": "Unauthorized" },
          "403": { "description": "Not a participant" },
          "409": { "description": "Exchange readiness not satisfied for both students" }
        }
      }
    },
    "/api/v1/matching/form1": {
      "post": {
        "summary": "Save match profile (Form 1)",
        "description": "Student only. Updates full name, university, replaces offered/requested skills not tied to an Exchange.",
        "tags": ["Matching"],
        "security": [{ "bearerAuth": [] }],
        "requestBody": {
          "required": true,
          "content": {
            "application/json": {
              "schema": { "$ref": "#/components/schemas/MatchForm1Request" }
            }
          }
        },
        "responses": {
          "200": { "description": "Saved" },
          "400": { "description": "Validation error" },
          "401": { "description": "Unauthorized" },
          "403": { "description": "Student required" },
          "404": { "description": "University or user not found" }
        }
      }
    },
    "/api/v1/matching/check": {
      "get": {
        "summary": "Check mutual match with another student",
        "description": "Student only. Query: otherStudentId (integer). Returns matched and directional pair hints.",
        "tags": ["Matching"],
        "security": [{ "bearerAuth": [] }],
        "parameters": [
          { "name": "otherStudentId", "in": "query", "required": true, "schema": { "type": "integer", "minimum": 1 } }
        ],
        "responses": {
          "200": { "description": "Match evaluation", "content": { "application/json": { "schema": { "$ref": "#/components/schemas/MatchCheckResponse" } } } },
          "401": { "description": "Unauthorized" },
          "403": { "description": "Student required" }
        }
      }
    },
    "/api/v1/matching/conversations/{conversationId}/form2-eligibility": {
      "get": {
        "summary": "Form 2 eligibility for a conversation",
        "description": "Student participant only. Returns suggested offer/request pairs, mutualSwapReady, and exchangeReadiness (iAmReady, peerReady, bothReady).",
        "tags": ["Matching"],
        "security": [{ "bearerAuth": [] }],
        "parameters": [
          { "name": "conversationId", "in": "path", "required": true, "schema": { "type": "integer" } }
        ],
        "responses": {
          "200": { "description": "Eligibility payload" },
          "401": { "description": "Unauthorized" },
          "403": { "description": "Not a participant" },
          "404": { "description": "Conversation not found" }
        }
      }
    },
    "/api/v1/universities": {
      "get": {
        "summary": "List universities",
        "description": "Public (e.g. for registration dropdown).",
        "tags": ["Universities"],
        "responses": {
          "200": { "description": "List of universities" }
        }
      },
      "post": {
        "summary": "Create university",
        "description": "Superadmin only.",
        "tags": ["Universities"],
        "security": [{ "bearerAuth": [] }],
        "requestBody": {
          "required": true,
          "content": {
            "application/json": {
              "schema": {
                "type": "object",
                "required": ["universityName", "address", "contactEmail"],
                "properties": {
                  "universityName": { "type": "string" },
                  "address": { "type": "string" },
                  "contactEmail": { "type": "string", "format": "email" }
                }
              }
            }
          }
        },
        "responses": {
          "201": { "description": "Created" },
          "400": { "description": "Validation error" },
          "401": { "description": "Unauthorized" },
          "403": { "description": "Superadmin required" }
        }
      }
    },
    "/api/v1/universities/{id}": {
      "get": {
        "summary": "Get university by ID",
        "description": "Public.",
        "tags": ["Universities"],
        "parameters": [
          { "name": "id", "in": "path", "required": true, "schema": { "type": "integer" } }
        ],
        "responses": {
          "200": { "description": "University" },
          "404": { "description": "Not found" }
        }
      },
      "put": {
        "summary": "Update university",
        "description": "Superadmin only.",
        "tags": ["Universities"],
        "security": [{ "bearerAuth": [] }],
        "parameters": [
          { "name": "id", "in": "path", "required": true, "schema": { "type": "integer" } }
        ],
        "requestBody": {
          "required": true,
          "content": {
            "application/json": {
              "schema": {
                "type": "object",
                "required": ["universityName", "address", "contactEmail"],
                "properties": {
                  "universityName": { "type": "string" },
                  "address": { "type": "string" },
                  "contactEmail": { "type": "string", "format": "email" }
                }
              }
            }
          }
        },
        "responses": {
          "200": { "description": "Updated" },
          "400": { "description": "Validation error" },
          "401": { "description": "Unauthorized" },
          "403": { "description": "Superadmin required" },
          "404": { "description": "Not found" }
        }
      },
      "delete": {
        "summary": "Delete university",
        "description": "Superadmin only.",
        "tags": ["Universities"],
        "security": [{ "bearerAuth": [] }],
        "parameters": [
          { "name": "id", "in": "path", "required": true, "schema": { "type": "integer" } }
        ],
        "responses": {
          "200": { "description": "Deleted" },
          "400": { "description": "University has students/admins" },
          "401": { "description": "Unauthorized" },
          "403": { "description": "Superadmin required" },
          "404": { "description": "Not found" }
        }
      }
    },
    "/api/v1/skill-categories": {
      "get": {
        "summary": "List skill categories",
        "tags": ["Skill Categories"],
        "security": [{ "bearerAuth": [] }],
        "responses": {
          "200": { "description": "List" },
          "401": { "description": "Unauthorized" }
        }
      },
      "post": {
        "summary": "Create skill category",
        "description": "Superadmin only.",
        "tags": ["Skill Categories"],
        "security": [{ "bearerAuth": [] }],
        "requestBody": {
          "content": {
            "application/json": {
              "schema": {
                "type": "object",
                "properties": {
                  "categoryName": { "type": "string" }
                }
              }
            }
          }
        },
        "responses": {
          "201": { "description": "Created" },
          "400": { "description": "Validation error" },
          "401": { "description": "Unauthorized" },
          "403": { "description": "Superadmin required" }
        }
      }
    },
    "/api/v1/skill-categories/{id}": {
      "get": {
        "summary": "Get skill category by ID",
        "tags": ["Skill Categories"],
        "security": [{ "bearerAuth": [] }],
        "parameters": [
          { "name": "id", "in": "path", "required": true, "schema": { "type": "integer" } }
        ],
        "responses": {
          "200": { "description": "Found" },
          "401": { "description": "Unauthorized" },
          "404": { "description": "Not found" }
        }
      },
      "put": {
        "summary": "Update skill category",
        "description": "Superadmin only.",
        "tags": ["Skill Categories"],
        "security": [{ "bearerAuth": [] }],
        "parameters": [
          { "name": "id", "in": "path", "required": true, "schema": { "type": "integer" } }
        ],
        "responses": {
          "200": { "description": "Updated" },
          "400": { "description": "Validation error" },
          "401": { "description": "Unauthorized" },
          "403": { "description": "Superadmin required" },
          "404": { "description": "Not found" }
        }
      },
      "delete": {
        "summary": "Delete skill category",
        "description": "Superadmin only.",
        "tags": ["Skill Categories"],
        "security": [{ "bearerAuth": [] }],
        "parameters": [
          { "name": "id", "in": "path", "required": true, "schema": { "type": "integer" } }
        ],
        "responses": {
          "200": { "description": "Deleted" },
          "401": { "description": "Unauthorized" },
          "403": { "description": "Superadmin required" },
          "404": { "description": "Not found" }
        }
      }
    },
    "/api/v1/skills": {
      "get": {
        "summary": "List skills",
        "tags": ["Skills"],
        "security": [{ "bearerAuth": [] }],
        "responses": {
          "200": { "description": "List" },
          "401": { "description": "Unauthorized" }
        }
      },
      "post": {
        "summary": "Create skill",
        "description": "Superadmin only.",
        "tags": ["Skills"],
        "security": [{ "bearerAuth": [] }],
        "requestBody": {
          "content": {
            "application/json": {
              "schema": {
                "type": "object",
                "properties": {
                  "categoryId": { "type": "integer" },
                  "skillName": { "type": "string" },
                  "difficultyLevel": { "type": "string", "enum": ["beginner", "intermediate", "advanced"] }
                }
              }
            }
          }
        },
        "responses": {
          "201": { "description": "Created" },
          "400": { "description": "Validation error" },
          "401": { "description": "Unauthorized" },
          "403": { "description": "Superadmin required" }
        }
      }
    },
    "/api/v1/skills/{id}": {
      "get": {
        "summary": "Get skill by ID",
        "tags": ["Skills"],
        "security": [{ "bearerAuth": [] }],
        "parameters": [
          { "name": "id", "in": "path", "required": true, "schema": { "type": "integer" } }
        ],
        "responses": {
          "200": { "description": "Found" },
          "401": { "description": "Unauthorized" },
          "404": { "description": "Not found" }
        }
      },
      "put": {
        "summary": "Update skill",
        "description": "Superadmin only.",
        "tags": ["Skills"],
        "security": [{ "bearerAuth": [] }],
        "parameters": [
          { "name": "id", "in": "path", "required": true, "schema": { "type": "integer" } }
        ],
        "responses": {
          "200": { "description": "Updated" },
          "400": { "description": "Validation error" },
          "401": { "description": "Unauthorized" },
          "403": { "description": "Superadmin required" },
          "404": { "description": "Not found" }
        }
      },
      "delete": {
        "summary": "Delete skill",
        "description": "Superadmin only.",
        "tags": ["Skills"],
        "security": [{ "bearerAuth": [] }],
        "parameters": [
          { "name": "id", "in": "path", "required": true, "schema": { "type": "integer" } }
        ],
        "responses": {
          "200": { "description": "Deleted" },
          "401": { "description": "Unauthorized" },
          "403": { "description": "Superadmin required" },
          "404": { "description": "Not found" }
        }
      }
    },
    "/api/v1/offered-skills": {
      "get": {
        "summary": "List offered skills",
        "description": "Query: ?mine=true for own offers.",
        "tags": ["Offered Skills"],
        "security": [{ "bearerAuth": [] }],
        "responses": {
          "200": { "description": "List" },
          "401": { "description": "Unauthorized" }
        }
      },
      "post": {
        "summary": "Create offered skill",
        "description": "Student only.",
        "tags": ["Offered Skills"],
        "security": [{ "bearerAuth": [] }],
        "requestBody": {
          "content": {
            "application/json": {
              "schema": {
                "type": "object",
                "properties": {
                  "skillId": { "type": "integer" },
                  "isPaid": { "type": "boolean" },
                  "pricePerHour": { "type": "number" }
                }
              }
            }
          }
        },
        "responses": {
          "201": { "description": "Created" },
          "400": { "description": "Validation error" },
          "401": { "description": "Unauthorized" },
          "403": { "description": "Student required" }
        }
      }
    },
    "/api/v1/offered-skills/{id}": {
      "get": {
        "summary": "Get offered skill by ID",
        "tags": ["Offered Skills"],
        "security": [{ "bearerAuth": [] }],
        "parameters": [
          { "name": "id", "in": "path", "required": true, "schema": { "type": "integer" } }
        ],
        "responses": {
          "200": { "description": "Found" },
          "401": { "description": "Unauthorized" },
          "404": { "description": "Not found" }
        }
      },
      "put": {
        "summary": "Update offered skill",
        "description": "Student only.",
        "tags": ["Offered Skills"],
        "security": [{ "bearerAuth": [] }],
        "parameters": [
          { "name": "id", "in": "path", "required": true, "schema": { "type": "integer" } }
        ],
        "requestBody": {
          "content": {
            "application/json": {
              "schema": {
                "type": "object",
                "properties": {
                  "isPaid": { "type": "boolean" },
                  "pricePerHour": { "type": "number" }
                }
              }
            }
          }
        },
        "responses": {
          "200": { "description": "Updated" },
          "400": { "description": "Validation error" },
          "401": { "description": "Unauthorized" },
          "403": { "description": "Student required" },
          "404": { "description": "Not found" }
        }
      },
      "delete": {
        "summary": "Delete offered skill",
        "description": "Student only.",
        "tags": ["Offered Skills"],
        "security": [{ "bearerAuth": [] }],
        "parameters": [
          { "name": "id", "in": "path", "required": true, "schema": { "type": "integer" } }
        ],
        "responses": {
          "200": { "description": "Deleted" },
          "401": { "description": "Unauthorized" },
          "403": { "description": "Student required" },
          "404": { "description": "Not found" }
        }
      }
    },
    "/api/v1/requested-skills": {
      "get": {
        "summary": "List requested skills",
        "description": "Query: ?mine=true for own requests.",
        "tags": ["Requested Skills"],
        "security": [{ "bearerAuth": [] }],
        "responses": {
          "200": { "description": "List" },
          "401": { "description": "Unauthorized" }
        }
      },
      "post": {
        "summary": "Create requested skill",
        "description": "Student only.",
        "tags": ["Requested Skills"],
        "security": [{ "bearerAuth": [] }],
        "requestBody": {
          "content": {
            "application/json": {
              "schema": {
                "type": "object",
                "properties": {
                  "skillId": { "type": "integer" },
                  "preferredTime": { "type": "string" },
                  "preferredMode": { "type": "string", "enum": ["Exchange", "Paid"] }
                }
              }
            }
          }
        },
        "responses": {
          "201": { "description": "Created" },
          "400": { "description": "Validation error" },
          "401": { "description": "Unauthorized" },
          "403": { "description": "Student required" }
        }
      }
    },
    "/api/v1/requested-skills/{id}": {
      "get": {
        "summary": "Get requested skill by ID",
        "tags": ["Requested Skills"],
        "security": [{ "bearerAuth": [] }],
        "parameters": [
          { "name": "id", "in": "path", "required": true, "schema": { "type": "integer" } }
        ],
        "responses": {
          "200": { "description": "Found" },
          "401": { "description": "Unauthorized" },
          "404": { "description": "Not found" }
        }
      },
      "delete": {
        "summary": "Delete requested skill",
        "description": "Student only.",
        "tags": ["Requested Skills"],
        "security": [{ "bearerAuth": [] }],
        "parameters": [
          { "name": "id", "in": "path", "required": true, "schema": { "type": "integer" } }
        ],
        "responses": {
          "200": { "description": "Deleted" },
          "401": { "description": "Unauthorized" },
          "403": { "description": "Student required" },
          "404": { "description": "Not found" }
        }
      }
    },
    "/api/v1/requested-skills/{id}/status": {
      "patch": {
        "summary": "Update requested skill status",
        "description": "Student only. Body: { status }. Enum: open, matched, closed.",
        "tags": ["Requested Skills"],
        "security": [{ "bearerAuth": [] }],
        "parameters": [
          { "name": "id", "in": "path", "required": true, "schema": { "type": "integer" } }
        ],
        "requestBody": {
          "content": {
            "application/json": {
              "schema": {
                "type": "object",
                "properties": {
                  "status": { "type": "string", "enum": ["open", "matched", "closed"] }
                }
              }
            }
          }
        },
        "responses": {
          "200": { "description": "Updated" },
          "400": { "description": "Validation error" },
          "401": { "description": "Unauthorized" },
          "403": { "description": "Student required" },
          "404": { "description": "Not found" }
        }
      }
    },
    "/api/v1/conversations": {
      "get": {
        "summary": "List conversations",
        "description": "Student only. Returns conversations where the current user is a participant.",
        "tags": ["Conversations"],
        "security": [{ "bearerAuth": [] }],
        "responses": {
          "200": {
            "description": "List of conversations",
            "content": {
              "application/json": {
                "schema": {
                  "type": "object",
                  "properties": {
                    "success": { "type": "boolean", "example": true },
                    "data": {
                      "type": "array",
                      "items": { "$ref": "#/components/schemas/Conversation" }
                    }
                  }
                }
              }
            }
          },
          "401": { "description": "Unauthorized" },
          "403": { "description": "Student required" }
        }
      }
    },
    "/api/v1/conversations/get-or-create": {
      "post": {
        "summary": "Get or create conversation",
        "description": "Student only. Body: { otherStudentId }.",
        "tags": ["Conversations"],
        "security": [{ "bearerAuth": [] }],
        "requestBody": {
          "required": true,
          "content": {
            "application/json": {
              "schema": {
                "type": "object",
                "required": ["otherStudentId"],
                "properties": {
                  "otherStudentId": { "type": "integer" }
                }
              }
            }
          }
        },
        "responses": {
          "200": {
            "description": "Existing conversation",
            "content": {
              "application/json": {
                "schema": {
                  "type": "object",
                  "properties": {
                    "success": { "type": "boolean", "example": true },
                    "data": { "$ref": "#/components/schemas/Conversation" }
                  }
                }
              }
            }
          },
          "201": {
            "description": "New conversation created",
            "content": {
              "application/json": {
                "schema": {
                  "type": "object",
                  "properties": {
                    "success": { "type": "boolean", "example": true },
                    "data": { "$ref": "#/components/schemas/Conversation" }
                  }
                }
              }
            }
          },
          "400": { "description": "Validation error (e.g. invalid otherStudentId)" },
          "401": { "description": "Unauthorized" },
          "403": { "description": "Student required" },
          "409": { "description": "No mutual skill match — conversation not created" }
        }
      }
    },
    "/api/v1/conversations/{id}": {
      "get": {
        "summary": "Get conversation by ID",
        "description": "Student only. Caller must be a participant.",
        "tags": ["Conversations"],
        "security": [{ "bearerAuth": [] }],
        "parameters": [
          { "name": "id", "in": "path", "required": true, "schema": { "type": "integer" } }
        ],
        "responses": {
          "200": {
            "description": "Conversation",
            "content": {
              "application/json": {
                "schema": {
                  "type": "object",
                  "properties": {
                    "success": { "type": "boolean", "example": true },
                    "data": { "$ref": "#/components/schemas/Conversation" }
                  }
                }
              }
            }
          },
          "401": { "description": "Unauthorized" },
          "403": { "description": "Student required" },
          "404": { "description": "Not found" }
        }
      }
    },
    "/api/v1/conversations/{id}/exchange-readiness": {
      "patch": {
        "summary": "Set exchange readiness (Form 2 slider)",
        "description": "Student only. Body: { ready: boolean }. Emits `exchange_readiness` to the conversation Socket.io room.",
        "tags": ["Conversations"],
        "security": [{ "bearerAuth": [] }],
        "parameters": [
          { "name": "id", "in": "path", "required": true, "schema": { "type": "integer" } }
        ],
        "requestBody": {
          "required": true,
          "content": {
            "application/json": {
              "schema": {
                "type": "object",
                "required": ["ready"],
                "properties": { "ready": { "type": "boolean" } }
              }
            }
          }
        },
        "responses": {
          "200": { "description": "Updated conversation payload" },
          "400": { "description": "Validation error" },
          "401": { "description": "Unauthorized" },
          "403": { "description": "Not a participant" },
          "404": { "description": "Not found" }
        }
      }
    },
    "/api/v1/conversations/{id}/messages": {
      "get": {
        "summary": "List messages in conversation",
        "description": "Student only. Query: limit (default 100, max 200). Caller must be a participant.",
        "tags": ["Conversations"],
        "security": [{ "bearerAuth": [] }],
        "parameters": [
          { "name": "id", "in": "path", "required": true, "schema": { "type": "integer" } },
          { "name": "limit", "in": "query", "required": false, "schema": { "type": "integer", "default": 100 } }
        ],
        "responses": {
          "200": {
            "description": "List of messages",
            "content": {
              "application/json": {
                "schema": {
                  "type": "object",
                  "properties": {
                    "success": { "type": "boolean", "example": true },
                    "data": {
                      "type": "array",
                      "items": { "$ref": "#/components/schemas/Message" }
                    }
                  }
                }
              }
            }
          },
          "401": { "description": "Unauthorized" },
          "403": { "description": "Student required" },
          "404": { "description": "Not found" }
        }
      },
      "post": {
        "summary": "Send message",
        "description": "Student only. Body: { content }. Message is saved and then emitted over Socket.io to the conversation room so the other participant receives it in real time (listen for 'message' event).",
        "tags": ["Conversations"],
        "security": [{ "bearerAuth": [] }],
        "parameters": [
          { "name": "id", "in": "path", "required": true, "schema": { "type": "integer" } }
        ],
        "requestBody": {
          "required": true,
          "content": {
            "application/json": {
              "schema": {
                "type": "object",
                "required": ["content"],
                "properties": {
                  "content": { "type": "string", "minLength": 1 }
                }
              }
            }
          }
        },
        "responses": {
          "201": {
            "description": "Message created; same payload is emitted via Socket.io to the conversation room.",
            "content": {
              "application/json": {
                "schema": {
                  "type": "object",
                  "properties": {
                    "success": { "type": "boolean", "example": true },
                    "data": { "$ref": "#/components/schemas/Message" }
                  }
                }
              }
            }
          },
          "400": { "description": "Validation error (e.g. empty content)" },
          "401": { "description": "Unauthorized" },
          "403": { "description": "Student required or not a participant" },
          "404": { "description": "Not found" }
        }
      }
    },
    "/api/v1/exchanges": {
      "get": {
        "summary": "List exchanges",
        "description": "Student: own; Admin/Superadmin: scoped.",
        "tags": ["Exchanges"],
        "security": [{ "bearerAuth": [] }],
        "responses": {
          "200": { "description": "List" },
          "401": { "description": "Unauthorized" },
          "403": { "description": "Forbidden" }
        }
      }
    },
    "/api/v1/exchanges/{id}": {
      "get": {
        "summary": "Get exchange by ID",
        "tags": ["Exchanges"],
        "security": [{ "bearerAuth": [] }],
        "parameters": [
          { "name": "id", "in": "path", "required": true, "schema": { "type": "integer" } }
        ],
        "responses": {
          "200": { "description": "Found" },
          "401": { "description": "Unauthorized" },
          "403": { "description": "Forbidden" },
          "404": { "description": "Not found" }
        }
      }
    },
    "/api/v1/exchanges/{id}/status": {
      "patch": {
        "summary": "Update exchange status",
        "description": "Body: { status }. Enum: pending, active, completed, cancelled. Student (participant), Admin, or Superadmin.",
        "tags": ["Exchanges"],
        "security": [{ "bearerAuth": [] }],
        "parameters": [
          { "name": "id", "in": "path", "required": true, "schema": { "type": "integer" } }
        ],
        "requestBody": {
          "content": {
            "application/json": {
              "schema": {
                "type": "object",
                "properties": {
                  "status": { "type": "string", "enum": ["pending", "active", "completed", "cancelled"] }
                }
              }
            }
          }
        },
        "responses": {
          "200": { "description": "Updated" },
          "400": { "description": "Validation error" },
          "401": { "description": "Unauthorized" },
          "403": { "description": "Forbidden" },
          "404": { "description": "Not found" }
        }
      }
    },
    "/api/v1/sessions": {
      "get": {
        "summary": "List sessions",
        "description": "Query: ?exchangeId=. Student only.",
        "tags": ["Sessions"],
        "security": [{ "bearerAuth": [] }],
        "parameters": [
          { "name": "exchangeId", "in": "query", "schema": { "type": "integer" } }
        ],
        "responses": {
          "200": { "description": "List" },
          "401": { "description": "Unauthorized" },
          "403": { "description": "Student required" }
        }
      }
    },
    "/api/v1/sessions/{id}": {
      "get": {
        "summary": "Get session by ID",
        "tags": ["Sessions"],
        "security": [{ "bearerAuth": [] }],
        "parameters": [
          { "name": "id", "in": "path", "required": true, "schema": { "type": "integer" } }
        ],
        "responses": {
          "200": { "description": "Found" },
          "401": { "description": "Unauthorized" },
          "403": { "description": "Student required" },
          "404": { "description": "Not found" }
        }
      }
    },
    "/api/v1/sessions/{id}/status": {
      "patch": {
        "summary": "Update session status",
        "description": "Body: { status }. Enum: scheduled, ongoing, completed, cancelled. Student only.",
        "tags": ["Sessions"],
        "security": [{ "bearerAuth": [] }],
        "parameters": [
          { "name": "id", "in": "path", "required": true, "schema": { "type": "integer" } }
        ],
        "requestBody": {
          "content": {
            "application/json": {
              "schema": {
                "type": "object",
                "properties": {
                  "status": { "type": "string", "enum": ["scheduled", "ongoing", "completed", "cancelled"] }
                }
              }
            }
          }
        },
        "responses": {
          "200": { "description": "Updated" },
          "400": { "description": "Validation error" },
          "401": { "description": "Unauthorized" },
          "403": { "description": "Student required" },
          "404": { "description": "Not found" }
        }
      }
    },
    "/api/v1/reviews": {
      "get": {
        "summary": "List reviews",
        "description": "Query: ?exchangeId= or ?revieweeId=.",
        "tags": ["Reviews"],
        "security": [{ "bearerAuth": [] }],
        "responses": {
          "200": { "description": "List" },
          "401": { "description": "Unauthorized" }
        }
      },
      "post": {
        "summary": "Create review",
        "description": "Student only. Body: revieweeId, rating (1-5), exchangeId/sessionId optional, feedback optional.",
        "tags": ["Reviews"],
        "security": [{ "bearerAuth": [] }],
        "requestBody": {
          "required": true,
          "content": {
            "application/json": {
              "schema": {
                "type": "object",
                "required": ["revieweeId", "rating"],
                "properties": {
                  "revieweeId": { "type": "integer" },
                  "rating": { "type": "integer", "minimum": 1, "maximum": 5 },
                  "exchangeId": { "type": "integer" },
                  "sessionId": { "type": "integer" },
                  "feedback": { "type": "string" }
                }
              }
            }
          }
        },
        "responses": {
          "201": { "description": "Created" },
          "400": { "description": "Validation error" },
          "401": { "description": "Unauthorized" },
          "403": { "description": "Student required" }
        }
      }
    },
    "/api/v1/reviews/{id}": {
      "get": {
        "summary": "Get review by ID",
        "tags": ["Reviews"],
        "security": [{ "bearerAuth": [] }],
        "parameters": [
          { "name": "id", "in": "path", "required": true, "schema": { "type": "integer" } }
        ],
        "responses": {
          "200": { "description": "Found" },
          "401": { "description": "Unauthorized" },
          "404": { "description": "Not found" }
        }
      }
    },
    "/api/v1/portfolio": {
      "get": {
        "summary": "List portfolio items",
        "description": "Query: ?studentId= or mine.",
        "tags": ["Portfolio"],
        "security": [{ "bearerAuth": [] }],
        "responses": {
          "200": { "description": "List" },
          "401": { "description": "Unauthorized" }
        }
      },
      "post": {
        "summary": "Create portfolio item",
        "description": "Student only.",
        "tags": ["Portfolio"],
        "security": [{ "bearerAuth": [] }],
        "requestBody": {
          "content": {
            "application/json": {
              "schema": {
                "type": "object",
                "properties": {
                  "skillId": { "type": "integer" },
                  "description": { "type": "string" }
                }
              }
            }
          }
        },
        "responses": {
          "201": { "description": "Created" },
          "400": { "description": "Validation error" },
          "401": { "description": "Unauthorized" },
          "403": { "description": "Student required" }
        }
      }
    },
    "/api/v1/portfolio/{id}": {
      "get": {
        "summary": "Get portfolio item by ID",
        "tags": ["Portfolio"],
        "security": [{ "bearerAuth": [] }],
        "parameters": [
          { "name": "id", "in": "path", "required": true, "schema": { "type": "integer" } }
        ],
        "responses": {
          "200": { "description": "Found" },
          "401": { "description": "Unauthorized" },
          "404": { "description": "Not found" }
        }
      },
      "put": {
        "summary": "Update portfolio item",
        "description": "Student only.",
        "tags": ["Portfolio"],
        "security": [{ "bearerAuth": [] }],
        "parameters": [
          { "name": "id", "in": "path", "required": true, "schema": { "type": "integer" } }
        ],
        "requestBody": {
          "content": {
            "application/json": {
              "schema": {
                "type": "object",
                "properties": {
                  "description": { "type": "string" }
                }
              }
            }
          }
        },
        "responses": {
          "200": { "description": "Updated" },
          "400": { "description": "Validation error" },
          "401": { "description": "Unauthorized" },
          "403": { "description": "Student required" },
          "404": { "description": "Not found" }
        }
      },
      "delete": {
        "summary": "Delete portfolio item",
        "description": "Student only.",
        "tags": ["Portfolio"],
        "security": [{ "bearerAuth": [] }],
        "parameters": [
          { "name": "id", "in": "path", "required": true, "schema": { "type": "integer" } }
        ],
        "responses": {
          "200": { "description": "Deleted" },
          "401": { "description": "Unauthorized" },
          "403": { "description": "Student required" },
          "404": { "description": "Not found" }
        }
      }
    },
    "/api/v1/payments": {
      "get": {
        "summary": "List payments",
        "description": "Admin/Superadmin.",
        "tags": ["Payments"],
        "security": [{ "bearerAuth": [] }],
        "responses": {
          "200": { "description": "List" },
          "401": { "description": "Unauthorized" }
        }
      }
    },
    "/api/v1/payments/{id}": {
      "get": {
        "summary": "Get payment by ID",
        "tags": ["Payments"],
        "security": [{ "bearerAuth": [] }],
        "parameters": [
          { "name": "id", "in": "path", "required": true, "schema": { "type": "integer" } }
        ],
        "responses": {
          "200": { "description": "Found" },
          "401": { "description": "Unauthorized" },
          "404": { "description": "Not found" }
        }
      }
    },
    "/api/v1/skill-questions": {
      "get": {
        "summary": "List skill questions",
        "description": "Query: ?skillId=.",
        "tags": ["Skill Questions"],
        "security": [{ "bearerAuth": [] }],
        "responses": {
          "200": { "description": "List" },
          "401": { "description": "Unauthorized" }
        }
      },
      "post": {
        "summary": "Create skill question",
        "description": "Admin or Superadmin.",
        "tags": ["Skill Questions"],
        "security": [{ "bearerAuth": [] }],
        "requestBody": {
          "content": {
            "application/json": {
              "schema": {
                "type": "object",
                "properties": {
                  "skillId": { "type": "integer" },
                  "questionText": { "type": "string" },
                  "correctAnswer": { "type": "string" },
                  "points": { "type": "integer" },
                  "options": { "type": "array" }
                }
              }
            }
          }
        },
        "responses": {
          "201": { "description": "Created" },
          "400": { "description": "Validation error" },
          "401": { "description": "Unauthorized" },
          "403": { "description": "Admin/Superadmin required" }
        }
      }
    },
    "/api/v1/skill-questions/{id}": {
      "get": {
        "summary": "Get skill question by ID",
        "tags": ["Skill Questions"],
        "security": [{ "bearerAuth": [] }],
        "parameters": [
          { "name": "id", "in": "path", "required": true, "schema": { "type": "integer" } }
        ],
        "responses": {
          "200": { "description": "Found" },
          "401": { "description": "Unauthorized" },
          "404": { "description": "Not found" }
        }
      },
      "put": {
        "summary": "Update skill question",
        "description": "Admin or Superadmin.",
        "tags": ["Skill Questions"],
        "security": [{ "bearerAuth": [] }],
        "parameters": [
          { "name": "id", "in": "path", "required": true, "schema": { "type": "integer" } }
        ],
        "responses": {
          "200": { "description": "Updated" },
          "400": { "description": "Validation error" },
          "401": { "description": "Unauthorized" },
          "403": { "description": "Admin/Superadmin required" },
          "404": { "description": "Not found" }
        }
      },
      "delete": {
        "summary": "Delete skill question",
        "description": "Admin or Superadmin.",
        "tags": ["Skill Questions"],
        "security": [{ "bearerAuth": [] }],
        "parameters": [
          { "name": "id", "in": "path", "required": true, "schema": { "type": "integer" } }
        ],
        "responses": {
          "200": { "description": "Deleted" },
          "401": { "description": "Unauthorized" },
          "403": { "description": "Admin/Superadmin required" },
          "404": { "description": "Not found" }
        }
      }
    },
    "/api/v1/skill-evaluations": {
      "get": {
        "summary": "List skill evaluations",
        "description": "Admin: university-scoped; Superadmin: all; Student: query studentId (self or as allowed) or skillId (own attempts only). Evaluations are created by POST /skill-quiz/submit, not here.",
        "tags": ["Skill Evaluations"],
        "security": [{ "bearerAuth": [] }],
        "responses": {
          "200": { "description": "List" },
          "401": { "description": "Unauthorized" }
        }
      }
    },
    "/api/v1/skill-evaluations/{id}": {
      "get": {
        "summary": "Get skill evaluation by ID",
        "tags": ["Skill Evaluations"],
        "security": [{ "bearerAuth": [] }],
        "parameters": [
          { "name": "id", "in": "path", "required": true, "schema": { "type": "integer" } }
        ],
        "responses": {
          "200": { "description": "Found" },
          "401": { "description": "Unauthorized" },
          "404": { "description": "Not found" }
        }
      }
    },
    "/api/v1/admin/students": {
      "get": {
        "summary": "List students (university admin)",
        "description": "Admin only: students at their university.",
        "tags": ["Admin"],
        "security": [{ "bearerAuth": [] }],
        "responses": {
          "200": { "description": "List" },
          "401": { "description": "Unauthorized" },
          "403": { "description": "Admin required" }
        }
      }
    },
    "/api/v1/admin/students/{id}/verify": {
      "patch": {
        "summary": "Verify student",
        "description": "Admin only. Body: { verified: boolean }.",
        "tags": ["Admin"],
        "security": [{ "bearerAuth": [] }],
        "parameters": [
          { "name": "id", "in": "path", "required": true, "schema": { "type": "integer" } }
        ],
        "requestBody": {
          "required": true,
          "content": {
            "application/json": {
              "schema": {
                "type": "object",
                "required": ["verified"],
                "properties": {
                  "verified": { "type": "boolean" }
                }
              }
            }
          }
        },
        "responses": {
          "200": { "description": "Updated" },
          "400": { "description": "Validation error" },
          "401": { "description": "Unauthorized" },
          "403": { "description": "Admin required" },
          "404": { "description": "Not found" }
        }
      }
    },
    "/api/v1/admins": {
      "get": {
        "summary": "List admins",
        "description": "Superadmin only.",
        "tags": ["Admins"],
        "security": [{ "bearerAuth": [] }],
        "responses": {
          "200": { "description": "List" },
          "401": { "description": "Unauthorized" },
          "403": { "description": "Superadmin required" }
        }
      },
      "post": {
        "summary": "Create admin",
        "description": "Superadmin only.",
        "tags": ["Admins"],
        "security": [{ "bearerAuth": [] }],
        "requestBody": {
          "required": true,
          "content": {
            "application/json": {
              "schema": {
                "type": "object",
                "required": ["email", "password", "fullName", "universityId"],
                "properties": {
                  "email": { "type": "string", "format": "email" },
                  "password": { "type": "string", "minLength": 6 },
                  "fullName": { "type": "string" },
                  "universityId": { "type": "integer" },
                  "adminLevel": { "type": "string", "enum": ["standard", "superadmin"] }
                }
              }
            }
          }
        },
        "responses": {
          "201": { "description": "Created" },
          "400": { "description": "Validation error" },
          "401": { "description": "Unauthorized" },
          "403": { "description": "Superadmin required" }
        }
      }
    },
    "/api/v1/admins/{id}": {
      "get": {
        "summary": "Get admin by ID",
        "description": "Superadmin only.",
        "tags": ["Admins"],
        "security": [{ "bearerAuth": [] }],
        "parameters": [
          { "name": "id", "in": "path", "required": true, "schema": { "type": "integer" } }
        ],
        "responses": {
          "200": { "description": "Found" },
          "401": { "description": "Unauthorized" },
          "403": { "description": "Superadmin required" },
          "404": { "description": "Not found" }
        }
      },
      "put": {
        "summary": "Update admin",
        "description": "Superadmin only.",
        "tags": ["Admins"],
        "security": [{ "bearerAuth": [] }],
        "parameters": [
          { "name": "id", "in": "path", "required": true, "schema": { "type": "integer" } }
        ],
        "requestBody": {
          "content": {
            "application/json": {
              "schema": {
                "type": "object",
                "properties": {
                  "universityId": { "type": "integer" },
                  "adminLevel": { "type": "string", "enum": ["standard", "superadmin"] }
                }
              }
            }
          }
        },
        "responses": {
          "200": { "description": "Updated" },
          "400": { "description": "Validation error" },
          "401": { "description": "Unauthorized" },
          "403": { "description": "Superadmin required" },
          "404": { "description": "Not found" }
        }
      },
      "delete": {
        "summary": "Delete admin",
        "description": "Superadmin only.",
        "tags": ["Admins"],
        "security": [{ "bearerAuth": [] }],
        "parameters": [
          { "name": "id", "in": "path", "required": true, "schema": { "type": "integer" } }
        ],
        "responses": {
          "200": { "description": "Deleted" },
          "401": { "description": "Unauthorized" },
          "403": { "description": "Superadmin required" },
          "404": { "description": "Not found" }
        }
      }
    },
    "/api/v1/reports": {
      "get": {
        "summary": "Get reports",
        "description": "Admin: university-scoped stats (totalStudents, totalExchanges, totalPayments, totalPaymentAmount). Superadmin: platform stats including totalUniversities, totalStudents, and universitiesStudentCounts (array of { universityId, universityName, studentCount } per university).",
        "tags": ["Reports"],
        "security": [{ "bearerAuth": [] }],
        "responses": {
          "200": { "description": "Report data (shape depends on role; superadmin includes universitiesStudentCounts)" },
          "401": { "description": "Unauthorized" },
          "403": { "description": "Admin/Superadmin required" }
        }
      }
    },
    "/api/v1/reports/payment-trend": {
      "get": {
        "summary": "Monthly payment trend for charts",
        "description": "Returns per-month totalAmount (PKR) and paymentCount. Superadmin: all payments. Admin: payments where offerer is at admin university. Query: months (1–36, default 12).",
        "tags": ["Reports"],
        "security": [{ "bearerAuth": [] }],
        "parameters": [
          { "name": "months", "in": "query", "required": false, "schema": { "type": "integer", "minimum": 1, "maximum": 36, "default": 12 } }
        ],
        "responses": {
          "200": { "description": "{ success, data: { months, series: [{ period, totalAmount, paymentCount }] } }" },
          "401": { "description": "Unauthorized" },
          "403": { "description": "Admin/Superadmin required" }
        }
      }
    },
    "/api/v1/reports/exchange-trend": {
      "get": {
        "summary": "Monthly exchange volume for charts",
        "description": "Returns per-month exchangeCount by Exchange.CreatedAt. Superadmin: all exchanges. Admin: exchanges where offer or request student is at admin university.",
        "tags": ["Reports"],
        "security": [{ "bearerAuth": [] }],
        "parameters": [
          { "name": "months", "in": "query", "required": false, "schema": { "type": "integer", "minimum": 1, "maximum": 36, "default": 12 } }
        ],
        "responses": {
          "200": { "description": "{ success, data: { months, series: [{ period, exchangeCount }] } }" },
          "401": { "description": "Unauthorized" },
          "403": { "description": "Admin/Superadmin required" }
        }
      }
    },
    "/api/v1/reports/top-skills": {
      "get": {
        "summary": "Top skills by offers, requests, and exchanges",
        "description": "Superadmin: platform-wide. Admin: only students at your university. Query: limit (1–30, default 10).",
        "tags": ["Reports"],
        "security": [{ "bearerAuth": [] }],
        "parameters": [
          { "name": "limit", "in": "query", "required": false, "schema": { "type": "integer", "minimum": 1, "maximum": 30, "default": 10 } }
        ],
        "responses": {
          "200": { "description": "{ success, data: { limit, skills: [{ skillId, skillName, offerCount, requestCount, exchangeCount }] } }" },
          "401": { "description": "Unauthorized" },
          "403": { "description": "Admin/Superadmin required" }
        }
      }
    },
    "/api/v1/reports/university-leaderboard": {
      "get": {
        "summary": "Top universities by exchange involvement",
        "description": "Superadmin only. Counts exchanges where an offer or request student belongs to each university. Query: limit (1–30, default 10).",
        "tags": ["Reports"],
        "security": [{ "bearerAuth": [] }],
        "parameters": [
          { "name": "limit", "in": "query", "required": false, "schema": { "type": "integer", "minimum": 1, "maximum": 30, "default": 10 } }
        ],
        "responses": {
          "200": { "description": "{ success, data: { limit, universities: [{ universityId, universityName, exchangeCount }] } }" },
          "401": { "description": "Unauthorized" },
          "403": { "description": "Superadmin only" }
        }
      }
    }
  },
  "components": {
    "securitySchemes": {
      "bearerAuth": {
        "type": "http",
        "scheme": "bearer",
        "bearerFormat": "JWT",
        "description": "JWT from POST /auth/login or POST /auth/register. Header: Authorization: Bearer <token>"
      }
    },
    "schemas": {
      "RegisterRequest": {
        "type": "object",
        "required": ["email", "password", "fullName"],
        "properties": {
          "email": { "type": "string", "format": "email" },
          "password": { "type": "string", "minLength": 6 },
          "fullName": { "type": "string" },
          "phoneNumber": { "type": "string" },
          "universityId": { "type": "integer", "minimum": 1, "description": "Optional. If provided, creates Student row so user gets role student." }
        }
      },
      "LoginRequest": {
        "type": "object",
        "required": ["email", "password"],
        "properties": {
          "email": { "type": "string", "format": "email" },
          "password": { "type": "string" }
        }
      },
      "AuthUser": {
        "type": "object",
        "properties": {
          "id": { "type": "integer" },
          "email": { "type": "string" },
          "fullName": { "type": "string" },
          "role": { "type": "string", "enum": ["student", "admin", "superadmin"] },
          "phoneNumber": { "type": "string", "nullable": true }
        }
      },
      "AuthResponse": {
        "type": "object",
        "properties": {
          "success": { "type": "boolean" },
          "data": {
            "type": "object",
            "properties": {
              "user": { "$ref": "#/components/schemas/AuthUser" },
              "token": { "type": "string" }
            }
          }
        }
      },
      "HealthResponse": {
        "type": "object",
        "properties": {
          "success": { "type": "boolean" },
          "message": { "type": "string" }
        }
      },
      "ErrorResponse": {
        "type": "object",
        "properties": {
          "success": { "type": "boolean", "example": false },
          "error": { "type": "string" }
        }
      },
      "User": {
        "type": "object",
        "properties": {
          "id": { "type": "integer" },
          "name": { "type": "string" },
          "email": { "type": "string" }
        }
      },
      "UserListResponse": {
        "type": "object",
        "properties": {
          "success": { "type": "boolean" },
          "data": {
            "type": "array",
            "items": { "$ref": "#/components/schemas/User" }
          }
        }
      },
      "SingleUserResponse": {
        "type": "object",
        "properties": {
          "success": { "type": "boolean" },
          "data": { "$ref": "#/components/schemas/User" }
        }
      },
      "MatchRequestResponse": {
        "type": "object",
        "properties": {
          "success": { "type": "boolean" },
          "data": {
            "type": "object",
            "properties": {
              "exchangeId": { "type": "integer" },
              "sessionId": { "type": "integer" }
            }
          }
        }
      },
      "PaidExchangeResponse": {
        "type": "object",
        "properties": {
          "success": { "type": "boolean" },
          "data": {
            "type": "object",
            "properties": {
              "message": { "type": "string" }
            }
          }
        }
      },
      "Conversation": {
        "type": "object",
        "properties": {
          "id": { "type": "integer", "description": "ConversationID" },
          "student1Id": { "type": "integer" },
          "student2Id": { "type": "integer" },
          "createdAt": { "type": "string", "format": "date-time" },
          "student1ExchangeReady": { "type": "boolean" },
          "student2ExchangeReady": { "type": "boolean" },
          "myExchangeReady": { "type": "boolean", "description": "When viewer is a participant" },
          "peerExchangeReady": { "type": "boolean" }
        }
      },
      "MatchForm1Request": {
        "type": "object",
        "required": ["fullName", "universityId", "offered", "requested"],
        "properties": {
          "fullName": { "type": "string" },
          "universityId": { "type": "integer" },
          "offered": {
            "type": "array",
            "items": {
              "type": "object",
              "required": ["skillId", "isPaid"],
              "properties": {
                "skillId": { "type": "integer" },
                "isPaid": { "type": "boolean" },
                "pricePerHour": { "type": "number", "minimum": 0 }
              }
            }
          },
          "requested": {
            "type": "array",
            "items": {
              "type": "object",
              "required": ["skillId", "preferredTime", "preferredMode"],
              "properties": {
                "skillId": { "type": "integer" },
                "preferredTime": { "type": "string", "enum": ["Morning", "Evenings", "Weekdays", "Weekends", "Flexible"] },
                "preferredMode": { "type": "string", "enum": ["Exchange", "Paid"] }
              }
            }
          }
        }
      },
      "MatchCheckResponse": {
        "type": "object",
        "properties": {
          "success": { "type": "boolean" },
          "data": {
            "type": "object",
            "properties": {
              "matched": { "type": "boolean" },
              "aLearnsFromB": { "type": "object", "nullable": true },
              "bLearnsFromA": { "type": "object", "nullable": true }
            }
          }
        }
      },
      "ConfirmForm2Request": {
        "type": "object",
        "required": ["conversationId", "meetingType", "venue", "scheduledStart", "scheduledEnd", "pairs"],
        "properties": {
          "conversationId": { "type": "integer" },
          "meetingType": { "type": "string", "enum": ["physical", "online"] },
          "venue": { "type": "string" },
          "scheduledStart": { "type": "string", "description": "MySQL DATETIME string" },
          "scheduledEnd": { "type": "string" },
          "pairs": {
            "type": "array",
            "items": {
              "type": "object",
              "required": ["offerId", "requestId"],
              "properties": {
                "offerId": { "type": "integer" },
                "requestId": { "type": "integer" },
                "agreedPrice": { "type": "number", "minimum": 0.01 }
              }
            }
          },
          "videoSession": {
            "type": "object",
            "properties": {
              "platform": { "type": "string" },
              "meetingLink": { "type": "string" },
              "meetingPassword": { "type": "string" }
            }
          }
        }
      },
      "ConfirmForm2Response": {
        "type": "object",
        "properties": {
          "success": { "type": "boolean" },
          "data": {
            "type": "object",
            "properties": {
              "exchangeIds": { "type": "array", "items": { "type": "integer" } },
              "sessionIds": { "type": "array", "items": { "type": "integer" } }
            }
          }
        }
      },
      "Message": {
        "type": "object",
        "properties": {
          "id": { "type": "integer", "description": "MessageID" },
          "conversationId": { "type": "integer" },
          "senderId": { "type": "integer" },
          "senderName": { "type": "string" },
          "content": { "type": "string" },
          "isRead": { "type": "boolean" },
          "createdAt": { "type": "string", "format": "date-time" }
        }
      }
    }
  }
}
